Metadata-Version: 1.0
Name: chikfactor
Version: 1.0
Summary: Calculate K-factor for EM production of chi in NRQCD
Home-page: https://github.com/SchneePingu/chikfactor
Author: Daniel Mueller
Author-email: xdaniel.muellerx@gmx.de
License: MIT
Platform: UNKNOWN
